ZeptojsApiDoc/README.md
ZeptojsApiDoc/__init__.py
ZeptojsApiDoc/__main__.py
ZeptojsApiDoc/file.epub
ZeptojsApiDoc/index.html
ZeptojsApiDoc/css/__init__.py
ZeptojsApiDoc/css/annotations.css
ZeptojsApiDoc/css/main.css
ZeptojsApiDoc/css/normalize.css
ZeptojsApiDoc/css/popup.css
ZeptojsApiDoc/font/__init__.py
ZeptojsApiDoc/font/fontello.eot
ZeptojsApiDoc/font/fontello.svg
ZeptojsApiDoc/font/fontello.ttf
ZeptojsApiDoc/font/fontello.woff
ZeptojsApiDoc/img/__init__.py
ZeptojsApiDoc/img/annotator-glyph-sprite.png
ZeptojsApiDoc/img/annotator-icon-sprite.png
ZeptojsApiDoc/img/apple-touch-icon.png
ZeptojsApiDoc/img/cancelfullscreen.png
ZeptojsApiDoc/img/close.png
ZeptojsApiDoc/img/fullscreen.png
ZeptojsApiDoc/img/loader.gif
ZeptojsApiDoc/img/menu-icon.png
ZeptojsApiDoc/img/save.png
ZeptojsApiDoc/img/saved.png
ZeptojsApiDoc/img/settings-s.png
ZeptojsApiDoc/img/settings.png
ZeptojsApiDoc/img/star.png
ZeptojsApiDoc/js/__init__.py
ZeptojsApiDoc/js/epub.js
ZeptojsApiDoc/js/epub.min.js
ZeptojsApiDoc/js/epub.min.map
ZeptojsApiDoc/js/hooks.min.js
ZeptojsApiDoc/js/hooks.min.map
ZeptojsApiDoc/js/reader.js
ZeptojsApiDoc/js/reader.js.map
ZeptojsApiDoc/js/reader.min.js
ZeptojsApiDoc/js/reader.min.map
ZeptojsApiDoc/js/hooks/__init__.py
ZeptojsApiDoc/js/hooks/extensions/__init__.py
ZeptojsApiDoc/js/hooks/extensions/highlight.js
ZeptojsApiDoc/js/libs/__init__.py
ZeptojsApiDoc/js/libs/jquery.min.js
ZeptojsApiDoc/js/libs/localforage.min.js
ZeptojsApiDoc/js/libs/screenfull.js
ZeptojsApiDoc/js/libs/screenfull.min.js
ZeptojsApiDoc/js/libs/zip.min.js
ZeptojsApiDoc/js/plugins/__init__.py
ZeptojsApiDoc/js/plugins/hypothesis.js
ZeptojsApiDoc/js/plugins/search.js
zeptojs_api_doc-2024.3.2.0.dist-info/METADATA
zeptojs_api_doc-2024.3.2.0.dist-info/WHEEL
zeptojs_api_doc-2024.3.2.0.dist-info/entry_points.txt
zeptojs_api_doc-2024.3.2.0.dist-info/top_level.txt
zeptojs_api_doc-2024.3.2.0.dist-info/RECORD
